[
  {
    "id": 1,
    "number": 1,
    "type": "single",
    "question": "党的二十大报告指出，我们对新时代党和国家事业发展作出科学完整的战略部署，提出实现（），以中国式现代化推进中华民族伟大复兴。",
    "options": {
      "A": "中国特色社会主义进入新时代",
      "B": "中华民族伟大复兴的中国梦",
      "C": "建成社会主义现代化强国",
      "D": "全面建成小康社会"
    },
    "answer": "B",
    "explanation": ""
  },
  {
    "id": 2,
    "number": 2,
    "type": "single",
    "question": "党的二十大报告指出，十年来，我们坚持走中国特色社会主义政治发展道路，全面发展（）人民民主。",
    "options": {
      "A": "全方位",
      "B": "多层次",
      "C": "全过程",
      "D": "整体"
    },
    "answer": "C",
    "explanation": ""
  },
  {
    "id": 3,
    "number": 3,
    "type": "single",
    "question": "二十大报告中指出，提高全社会文明程度，实施公民道德建设工程，弘扬中华传统美德，加强家庭家教家风建设，推动（）。①明大德；②守公德；③严私德",
    "options": {
      "A": "①②",
      "B": "①③",
      "C": "②③",
      "D": "①②③"
    },
    "answer": "D",
    "explanation": ""
  },
  {
    "id": 4,
    "number": 4,
    "type": "single",
    "question": "二十大报告中指出，治国有常，利民为本。（）是立党为公、执政为民的本质要求。",
    "options": {
      "A": "共同富裕",
      "B": "绿水青山",
      "C": "为民造福",
      "D": "脱贫攻坚"
    },
    "answer": "C",
    "explanation": ""
  },
  {
    "id": 5,
    "number": 5,
    "type": "single",
    "question": "党的二十大报告指出，要完善科技创新体系。坚持创新在我国现代化建设全局中的（）。",
    "options": {
      "A": "核心地位",
      "B": "首要地位",
      "C": "重要地位",
      "D": "中心地位"
    },
    "answer": "A",
    "explanation": ""
  },
  {
    "id": 6,
    "number": 6,
    "type": "single",
    "question": "党的二十大报告指出，要加快实施创新驱动发展战略。坚持面向世界科技前沿、面向经济主战场、面向国家重大需求、面向人民生命健康，加快实现高水平科技（）。",
    "options": {
      "A": "自立自强",
      "B": "自给自足",
      "C": "自产自销",
      "D": "走向世界"
    },
    "answer": "A",
    "explanation": ""
  },
  {
    "id": 7,
    "number": 7,
    "type": "single",
    "question": "二十大报告中指出，健全社会保障体系，健全（）的多层次社会保障体系，扩大社会保险覆盖面。①覆盖全民；②统筹城乡；③公平统一；④安全规范；⑤可持续",
    "options": {
      "A": "①②③④⑤",
      "B": "①②③④",
      "C": "①②③⑤",
      "D": "①②④⑤"
    },
    "answer": "A",
    "explanation": ""
  },
  {
    "id": 8,
    "number": 8,
    "type": "single",
    "question": "党的二十大报告指出，要支持和保证人民通过（）行使国家权力，保证各级人大都由民主选举产生、对人民负责、受人民监督。",
    "options": {
      "A": "法律法规",
      "B": "宪法",
      "C": "选举",
      "D": "人民代表大会"
    },
    "answer": "D",
    "explanation": ""
  },
  {
    "id": 9,
    "number": 9,
    "type": "single",
    "question": "党的二十大报告指出，我们要坚持（）在意识形态领域指导地位的根本制度。",
    "options": {
      "A": "中国特色社会主义",
      "B": "马克思主义",
      "C": "毛泽东思想",
      "D": "马列主义"
    },
    "answer": "B",
    "explanation": ""
  },
  {
    "id": 10,
    "number": 10,
    "type": "single",
    "question": "二十大报告中指出，必须贯彻新时代党的强军思想，贯彻新时代军事战略方针，坚持党对人民军队的绝对领导，坚持（）。①政治建军；②改革强军；③科技强军；④人才强军；⑤依法治军",
    "options": {
      "A": "①②③④⑤",
      "B": "①②③④",
      "C": "①②③⑤",
      "D": "①②④⑤"
    },
    "answer": "A",
    "explanation": ""
  },
  {
    "id": 11,
    "number": 11,
    "type": "single",
    "question": "二十大报告中指出，全面加强人民军队党的建设，确保枪杆子永远听党指挥。健全贯彻（）负责制体制机制。",
    "options": {
      "A": "军委书记",
      "B": "军委主席",
      "C": "国家主席",
      "D": "国家主席"
    },
    "answer": "B",
    "explanation": ""
  },
  {
    "id": 12,
    "number": 12,
    "type": "single",
    "question": "二十大报告中指出，（）是中国特色社会主义的伟大创举，是香港、澳门回归后保持长期繁荣稳定的最佳制度安排，必须长期坚持。",
    "options": {
      "A": "“高度自治”",
      "B": "“九二共识”",
      "C": "“一国两制”",
      "D": "“两岸一国”"
    },
    "answer": "C",
    "explanation": ""
  },
  {
    "id": 13,
    "number": 13,
    "type": "single",
    "question": "党的二十大报告强调，要完善以（ ）为核心的中国特色社会主义法律体系。",
    "options": {
      "A": "宪法",
      "B": "行政法",
      "C": "商法",
      "D": "民法"
    },
    "answer": "A",
    "explanation": ""
  },
  {
    "id": 14,
    "number": 14,
    "type": "single",
    "question": "二十大报告中指出，全面建设社会主义现代化国家、全面推进中华民族伟大复兴，关键在（）。",
    "options": {
      "A": "民",
      "B": "党",
      "C": "官",
      "D": "人"
    },
    "answer": "B",
    "explanation": ""
  },
  {
    "id": 15,
    "number": 15,
    "type": "single",
    "question": "二十大报告中指出，全面建设社会主义现代化国家，必须充分发挥亿万人民的创造伟力。全党要坚持（）的根本宗旨。",
    "options": {
      "A": "党中央权威和集中",
      "B": "人民当家作主",
      "C": "全心全意为人民服务",
      "D": "解放思想、实事求是"
    },
    "answer": "C",
    "explanation": ""
  },
  {
    "id": 16,
    "number": 16,
    "type": "single",
    "question": "二十大报告中指出，中国人民的（），中国共产党和中国人民正信心百倍推进中华民族从站起来、富起来到强起来的伟大飞跃。①前进动力更加强大；②奋斗精神更加昂扬；③必胜信念更加坚定",
    "options": {
      "A": "①②",
      "B": "①③",
      "C": "②③",
      "D": "①②③"
    },
    "answer": "D",
    "explanation": ""
  },
  {
    "id": 17,
    "number": 17,
    "type": "single",
    "question": "根据《习近平在中国共产党第二十次全国代表大会上的报告》中提到，推行草原森林河流湖泊湿地休养生息，实施好长江（ ）禁渔，健全耕地休耕轮作制度。",
    "options": {
      "A": "三年",
      "B": "五年",
      "C": "八年",
      "D": "十年"
    },
    "answer": "D",
    "explanation": ""
  },
  {
    "id": 18,
    "number": 18,
    "type": "single",
    "question": "二十大报告中指出，全党要把青年工作作为战略性工作来抓，用党的（）武装青年，用党的（）感召青年，做青年朋友的知心人、青年工作的热心人、青年群众的引路人。",
    "options": {
      "A": "理论实践；初心使命",
      "B": "科学理论；初心使命",
      "C": "理论实践；历史事",
      "D": "科学理论；历史事迹"
    },
    "answer": "B",
    "explanation": ""
  },
  {
    "id": 19,
    "number": 19,
    "type": "single",
    "question": "根据《习近平在中国共产党第二十次全国代表大会上的报告》中提到，完善党的自我革命制度规范体系。坚持制度治党、依规治党，健全党统一领导、（ ）、权威高效的监督体系。",
    "options": {
      "A": "全面加强",
      "B": "全面覆盖",
      "C": "全面推进",
      "D": "全面深化"
    },
    "answer": "B",
    "explanation": ""
  },
  {
    "id": 20,
    "number": 20,
    "type": "single",
    "question": "党的二十大报告中提到，大自然是人类赖以生存发展的基本条件。尊重自然、顺应自然、保护自然，是全面建设社会主义现代化国家的（ ）。",
    "options": {
      "A": "硬性要求",
      "B": "内在需要",
      "C": "内在要求",
      "D": "基本要求"
    },
    "answer": "C",
    "explanation": ""
  },
  {
    "id": 21,
    "number": 21,
    "type": "single",
    "question": "党的二十大报告中提到，立足我国能源资源禀赋，坚持先立后破，有计划分步骤实施（ ）。",
    "options": {
      "A": "碳达峰行动",
      "B": "碳节约行动",
      "C": "碳达标行动",
      "D": "碳峰值行动"
    },
    "answer": "A",
    "explanation": ""
  },
  {
    "id": 22,
    "number": 22,
    "type": "single",
    "question": "二十大报告中指出，我们实行更加积极主动的开放战略，共建“一带一路”成为深受欢迎的国际公共产品和国际合作平台，我国成为一百四十多个国家和地区的主要贸易伙伴，货物贸易总额居世界（）。",
    "options": {
      "A": "第四",
      "B": "第三",
      "C": "第二",
      "D": "第一"
    },
    "answer": "D",
    "explanation": ""
  },
  {
    "id": 23,
    "number": 23,
    "type": "single",
    "question": "党的二十大报告中提到，中国式现代化，是中国共产党领导的社会主义现代化，既有各国现代化的共同特征，更有基于自己国情的（ ）。",
    "options": {
      "A": "中国特色",
      "B": "中国理念",
      "C": "中国思路",
      "D": "中国方案"
    },
    "answer": "A",
    "explanation": ""
  },
  {
    "id": 24,
    "number": 24,
    "type": "single",
    "question": "党的二十大报告指出，十年来，我们深入贯彻（ ）的发展思想，在幼有所育、学有所教、劳有所得、病有所医、老有所养、住有所居、弱有所扶上持续用力，人民生活全方位改善。",
    "options": {
      "A": "人民至上",
      "B": "以人民为中心",
      "C": "以发展为中心",
      "D": "深化改革"
    },
    "answer": "B",
    "explanation": ""
  },
  {
    "id": 25,
    "number": 25,
    "type": "single",
    "question": "党的二十大报告指出，（ ）是我们立党立国、兴党兴国的根本指导思想。",
    "options": {
      "A": "马克思列宁主义",
      "B": "共产主义理论",
      "C": "马克思主义",
      "D": "科学社会主义"
    },
    "answer": "C",
    "explanation": ""
  },
  {
    "id": 26,
    "number": 26,
    "type": "single",
    "question": "二十大报告中指出，十年来，一些关键核心技术实现突破，战略性新兴产业发展壮大，（）等取得重大成果，进入创新型国家行列。①载人航天；②探月探火；③深海深地探测；④超级计算机；⑤卫星导航；⑥量子信息；⑦核电技术；⑧大飞机制造；⑨生物医药",
    "options": {
      "A": "①②③④⑤⑥",
      "B": "①③④⑤⑥⑦⑨",
      "C": "①②③⑤⑥⑦⑧⑨",
      "D": "①②③④⑤⑥⑦⑧⑨"
    },
    "answer": "D",
    "explanation": ""
  },
  {
    "id": 27,
    "number": 27,
    "type": "single",
    "question": "党的二十大报告指出，（ ）是党执政兴国的第一要务。没有坚实的物质技术基础，就不可能全面建成社会主义现代化强国。",
    "options": {
      "A": "发展",
      "B": "创新",
      "C": "改革",
      "D": "建设"
    },
    "answer": "A",
    "explanation": ""
  },
  {
    "id": 28,
    "number": 28,
    "type": "single",
    "question": "党的二十大报告指出，必须（ ）贯彻新发展理念，坚持社会主义市场经济改革方向，坚持高水平对外开放，加快构建以国内大循环为主体、国内国际双循环相互促进的新发展格局。",
    "options": {
      "A": "客观、公平、公正",
      "B": "完整、准确、全面",
      "C": "全面、客观、深入",
      "D": "坚定不移、不折不扣"
    },
    "answer": "B",
    "explanation": ""
  },
  {
    "id": 29,
    "number": 29,
    "type": "single",
    "question": "党的二十大报告指出，我们要坚持（）、（）、人才引领驱动，加快建设教育强国、科技强国、人才强国，坚持为党育人、为国育才，全面提高人才自主培养质量，着力造就拔尖创新人才，聚天下英才而用之。",
    "options": {
      "A": "教育优先发展；科技自立自强",
      "B": "守正创新；加速发展",
      "C": "以人为本；创新为先",
      "D": "稳扎稳打；大步前进"
    },
    "answer": "A",
    "explanation": ""
  },
  {
    "id": 30,
    "number": 30,
    "type": "single",
    "question": "二十大报告中指出，十九大、十九届六中全会提出的（）概括了习近平新时代中国特色社会主义思想的主要内容，必须长期坚持并不断丰富发展。①“十个明确”②“十四个坚持”③“十三个方面成就”",
    "options": {
      "A": "①②",
      "B": "①②",
      "C": "②③",
      "D": "①②③"
    },
    "answer": "D",
    "explanation": ""
  },
  {
    "id": 31,
    "number": 31,
    "type": "single",
    "question": "党的二十大报告指出，（ ）是社会主义民主政治的本质属性，是最广泛、最真实、最管用的民主。",
    "options": {
      "A": "人民至上",
      "B": "民主集中制",
      "C": "全过程人民民主",
      "D": "为人民服务"
    },
    "answer": "C",
    "explanation": ""
  },
  {
    "id": 32,
    "number": 32,
    "type": "single",
    "question": "党的二十大报告指出，全面建设社会主义现代化国家，必须坚持中国特色社会主义文化发展道路，增强文化自信，围绕（ ）、兴文化、展形象建设社会主义文化强国。",
    "options": {
      "A": "举旗帜、聚民心、育新人",
      "B": "守初心、聚民心、育人才",
      "C": "举旗帜、明方向、强使命",
      "D": "守初心、敢担当、善作为"
    },
    "answer": "A",
    "explanation": ""
  },
  {
    "id": 33,
    "number": 33,
    "type": "single",
    "question": "二十大报告中指出，前进道路上，必须牢牢把握以下重大原则∶（）。①坚持和加强党的全面领导；②坚持中国特色社会主义道路；③坚持以人民为中心的发展思想；④坚持深化改革开放；⑤坚持发扬斗争精神",
    "options": {
      "A": "①②③④⑤",
      "B": "①②③④",
      "C": "①②③⑤",
      "D": "①②④⑤"
    },
    "answer": "A",
    "explanation": ""
  },
  {
    "id": 34,
    "number": 34,
    "type": "single",
    "question": "二十大报告中指出，我们以巨大的政治勇气全面深化改革，许多领域实现（），中国特色社会主义制度更加成熟更加定型，国家治理体系和治理能力现代化水平明显提高。①历史性变革；②系统性重塑；③整体性重构",
    "options": {
      "A": "①②③",
      "B": "①②",
      "C": "①③",
      "D": "②③"
    },
    "answer": "A",
    "explanation": ""
  },
  {
    "id": 35,
    "number": 35,
    "type": "single",
    "question": "二十大报告中指出，全面推进乡村振兴，坚持农业农村优先发展，巩固拓展脱贫攻坚成果，加快建设农业强国，扎实推动乡村（）振兴。①产业；②人才；③文化；④生态；⑤组织",
    "options": {
      "A": "①②③④",
      "B": "①③④⑤",
      "C": "①②③④⑤",
      "D": "①②④⑤"
    },
    "answer": "C",
    "explanation": ""
  },
  {
    "id": 36,
    "number": 36,
    "type": "single",
    "question": "二十大报告中指出，全方位夯实粮食安全根基，牢牢守住（）亩耕地红线，确保中国人的饭碗牢牢端在自己手中。",
    "options": {
      "A": "十五亿",
      "B": "十六亿",
      "C": "十八亿",
      "D": "二十亿"
    },
    "answer": "C",
    "explanation": ""
  },
  {
    "id": 37,
    "number": 37,
    "type": "single",
    "question": "二十大报告指出，五年来、我们隆重庆祝中国共产党成立（）、中华人民共和国成立（），制定第三个历史决议，在全党开展党史学习教育，号召全党学习和践行伟大建党精神。",
    "options": {
      "A": "九十周年，六十周年",
      "B": "一百周年，六十周年",
      "C": "九十周年，七十周年",
      "D": "一百周年，七十周年"
    },
    "answer": "D",
    "explanation": ""
  },
  {
    "id": 38,
    "number": 38,
    "type": "single",
    "question": "二十大报告指出，必须坚持（）是第一生产力、（）是第一资源、（）是第一动力，深入实施科教兴国战略、人才强国战略、创新驱动发展战略，开辟发展新领域新赛道，不断塑造发展新动能新优势。",
    "options": {
      "A": "科技；矿产；改革",
      "B": "创新；矿产；改革",
      "C": "科技；人才；创新",
      "D": "创新；人才；科技"
    },
    "answer": "C",
    "explanation": ""
  },
  {
    "id": 39,
    "number": 39,
    "type": "single",
    "question": "二十大报告指出，我们全面加强党的领导，确保党中央权威和集中统一领导，确保党发挥总揽全局、协调各方的领导核心作用，我们这个拥有（）党员的马克思主义政党更加团结统一。",
    "options": {
      "A": "八千六百多万名",
      "B": "八千八百多万名",
      "C": "九千二百多万名",
      "D": "九千六百多万名"
    },
    "answer": "D",
    "explanation": ""
  },
  {
    "id": 40,
    "number": 40,
    "type": "single",
    "question": "二十大报告指出，我们要健全人民当家作主制度体系，扩大人民有序政治参与，保证人民依法实行（）。①民主选举；②民主协商；③民主决策；④民主管理；⑤民主监督",
    "options": {
      "A": "①②③④⑤",
      "B": "①②③④",
      "C": "①②③⑤",
      "D": "①②④⑤"
    },
    "answer": "A",
    "explanation": ""
  },
  {
    "id": 41,
    "number": 41,
    "type": "single",
    "question": "二十大报告中指出，（）是社会主义民主政治的本质属性，是最广泛、最真实、最管用的民主。必须坚定不移走中国特色社会主义政治发展道路，坚持党的领导、人民当家作主、依法治国有机统一。",
    "options": {
      "A": "全方位人民民主",
      "B": "全系统人民民主",
      "C": "全覆盖人民民主",
      "D": "全过程人民民主"
    },
    "answer": "D",
    "explanation": ""
  },
  {
    "id": 42,
    "number": 42,
    "type": "single",
    "question": "二十大报告中指出，十年来，我国经济实力实现历史性跃升，国内生产总值从五十四万亿元增长到（）。",
    "options": {
      "A": "九十万亿元",
      "B": "一百万亿元",
      "C": "一百零五万亿元",
      "D": "一百一十四万亿元"
    },
    "answer": "D",
    "explanation": ""
  },
  {
    "id": 43,
    "number": 43,
    "type": "single",
    "question": "二十大报告中指出，我国经济总量占世界经济的比重达（），提高7.2%，稳居世界（）。",
    "options": {
      "A": "15.8%；第一位",
      "B": "15.8%；第二位",
      "C": "18.5%，第一位",
      "D": "18.5%；第二位"
    },
    "answer": "D",
    "explanation": ""
  },
  {
    "id": 44,
    "number": 44,
    "type": "single",
    "question": "二十大报告中指出，十年来，人均国内生产总值从39800元增加到（）。",
    "options": {
      "A": "51000元",
      "B": "61000元",
      "C": "71000元",
      "D": "81000元"
    },
    "answer": "D",
    "explanation": ""
  },
  {
    "id": 45,
    "number": 45,
    "type": "single",
    "question": "二十大报告中指出，我国谷物总产量稳居世界（），制造业规模、外汇储备稳居世界（）。",
    "options": {
      "A": "首位；第一",
      "B": "首位；第二",
      "C": "第二；第一",
      "D": "第二；第一"
    },
    "answer": "A",
    "explanation": ""
  },
  {
    "id": 46,
    "number": 46,
    "type": "single",
    "question": "中国共产党第二十届中央委员会第二次全体会议，于2023年（ ）在北京举行。",
    "options": {
      "A": "1月26日至28日",
      "B": "2月26日至28日",
      "C": "3月26日至28日",
      "D": "4月26日至28日"
    },
    "answer": "B",
    "explanation": ""
  },
  {
    "id": 47,
    "number": 47,
    "type": "single",
    "question": "中国共产党第二十届中央委员会第二次全体会议认为，党的十八大以来，以习近平同志为核心的党中央把（）作为推进国家治理体系和治理能力现代化的一项重要任务。",
    "options": {
      "A": "深化党和国家机构改革",
      "B": "全面建设社会主义现代化国家",
      "C": "全面推进中华民族伟大复兴而团结奋斗",
      "D": "扎实推进社会主义民主法治建设和宣传思想文化工作"
    },
    "answer": "A",
    "explanation": ""
  },
  {
    "id": 48,
    "number": 48,
    "type": "single",
    "question": "中国共产党第二十届中央委员会第二次全体会议认为，（）是当前和今后一个时期全党的首要政治任务，要推动学习宣传贯彻往深里走、往实里走。",
    "options": {
      "A": "深入学习宣传贯彻党的二十大精神",
      "B": "加强和维护党中央集中统一领导",
      "C": "学习宣传贯彻党的二十大精神",
      "D": "深入学习贯彻习近平新时代中国特色社会主义思想和党的二十大精神"
    },
    "answer": "A",
    "explanation": ""
  },
  {
    "id": 49,
    "number": 49,
    "type": "single",
    "question": "中国共产党第二十届中央委员会第二次全体会议在北京举行。全会同意把《党和国家（ ）方案》的部分内容按照法定程序提交十四届全国人大一次会议审议。",
    "options": {
      "A": "经济发展",
      "B": "市场经济",
      "C": "经济改革",
      "D": "机构改革"
    },
    "answer": "D",
    "explanation": ""
  },
  {
    "id": 50,
    "number": 50,
    "type": "single",
    "question": "中国共产党第二十届中央委员会第二次全体会议强调，要坚持以（）强化正风肃纪，持续深化纠治“四风”，大兴调查研究之风，大力弘扬求真务实、真抓实干的作风，真正做出经得起历史和人民检验的实绩。",
    "options": {
      "A": "实事求是",
      "B": "求真务实",
      "C": "敢于担当",
      "D": "严的基调"
    },
    "answer": "D",
    "explanation": ""
  },
  {
    "id": 51,
    "number": 51,
    "type": "single",
    "question": "科学运用（ ）立场观点方法分析解决我国互联网发展治理问题，成为习近平新时代中国特色社会主义思想的重要组成部分。",
    "options": {
      "A": "社会主义",
      "B": "资本主义",
      "C": "马克思主义",
      "D": "官僚主义"
    },
    "answer": "C",
    "explanation": ""
  },
  {
    "id": 52,
    "number": 52,
    "type": "single",
    "question": "创造性提出构建网络空间命运共同体的理念主张，为全球互联网发展治理提出了（ ）、贡献了中国智慧。",
    "options": {
      "A": "中国道路",
      "B": "中国方案",
      "C": "中国思想",
      "D": "中国制度"
    },
    "answer": "B",
    "explanation": ""
  },
  {
    "id": 53,
    "number": 53,
    "type": "single",
    "question": "习近平总书记在（ ）首次提出“努力把我国建设成为网络强国”的战略目标。",
    "options": {
      "A": "2014年",
      "B": "2015年",
      "C": "2016年",
      "D": "2017年"
    },
    "answer": "A",
    "explanation": ""
  },
  {
    "id": 54,
    "number": 54,
    "type": "single",
    "question": "在新时代新征程上，我们需要始终（ ）并深刻把握其重大战略意义，坚持以习近平总书记关于网络强国的重要思想为指导，不断推动网络强国实现新目标、取得新发展、占领新高地？",
    "options": {
      "A": "坚持以习近平总书记关于网络强国的重要思想为指导",
      "B": "坚持以人为本的发展理念",
      "C": "坚持为人民服务",
      "D": "坚持爱国"
    },
    "answer": "A",
    "explanation": ""
  },
  {
    "id": 55,
    "number": 55,
    "type": "single",
    "question": "《中华人民共和国行政许可法》自（ ）起施行。",
    "options": {
      "A": "2004年7月1日",
      "B": "2003年7月2日",
      "C": "2004年7月2日",
      "D": "2004年8月1日"
    },
    "answer": "A",
    "explanation": ""
  },
  {
    "id": 56,
    "number": 56,
    "type": "single",
    "question": "根据《中华人民共和国行政许可法》，公民、法人或其他组织可以向（ ）机关提出关于行政许可的意见和建议。",
    "options": {
      "A": "行政许可的设定机关和实施机关",
      "B": "行政许可的立法机关和设定机关",
      "C": "行政许可的设定机关",
      "D": "立法机关"
    },
    "answer": "A",
    "explanation": ""
  },
  {
    "id": 57,
    "number": 57,
    "type": "single",
    "question": "根据《中华人民共和国行政许可法》，行政机关作出准予行政许可的决定后，应当自作出决定之日起（ ）日内向申请人颁发、送达行政许可证件。",
    "options": {
      "A": "三",
      "B": "五",
      "C": "七",
      "D": "十"
    },
    "answer": "D",
    "explanation": ""
  },
  {
    "id": 58,
    "number": 58,
    "type": "single",
    "question": "根据《中华人民共和国行政许可法》，行政机关依法变更或者撤回已经生效的行政许可时，给公民、法人或者其他组织造成财产损失的，行政机关应当依法（ ）。",
    "options": {
      "A": "给予赔偿",
      "B": "给予优待",
      "C": "给予补偿",
      "D": "追究责任"
    },
    "answer": "C",
    "explanation": ""
  },
  {
    "id": 59,
    "number": 59,
    "type": "single",
    "question": "根据《中华人民共和国行政许可法》，被许可人以欺骗、贿赂等不正当手段取得属于直接关系公共安全、人身健康、生命财产安全事项的行政许可，申请人在（ ）不得再次申请该行政许可。",
    "options": {
      "A": "一年内",
      "B": "三年内",
      "C": "五年内",
      "D": "永久"
    },
    "answer": "B",
    "explanation": ""
  },
  {
    "id": 60,
    "number": 60,
    "type": "single",
    "question": "根据《中华人民共和国行政许可法》，行政许可的实施和结果，除（ ）以外不得公开。",
    "options": {
      "A": "国家秘密",
      "B": "商业秘密",
      "C": "机关工作秘密",
      "D": "个人隐私"
    },
    "answer": "C",
    "explanation": ""
  },
  {
    "id": 61,
    "number": 61,
    "type": "single",
    "question": "根据《中华人民共和国行政许可法》，公民、法人或者其他组织依法取得的行政许可，下列说法错误的是( )",
    "options": {
      "A": "行政机关可以依法变更或者撤回已经生效的行政许可",
      "B": "行政机关不得擅自改变已经生效的行政许可",
      "C": "法律、法规规定依照法定条件和程序可以转让",
      "D": "行政机关根据情况可以撤销"
    },
    "answer": "D",
    "explanation": ""
  },
  {
    "id": 62,
    "number": 62,
    "type": "single",
    "question": "《中华人民共和国行政许可法》是在（ ）第十三届全国人民代表大会常务委员会第十次会议修正的。",
    "options": {
      "A": "2003年8月27日",
      "B": "2005年6月22日",
      "C": "2015年8月27日",
      "D": "2019年4月23日"
    },
    "answer": "D",
    "explanation": ""
  },
  {
    "id": 63,
    "number": 63,
    "type": "single",
    "question": "根据《中华人民共和国行政许可法》，被许可人需要延续依法取得的行政许可的有效期的，应当在该行政许可有效期届满（ ）日前向作出行政许可决定的行政机关提出申请。",
    "options": {
      "A": "十",
      "B": "二十",
      "C": "三十",
      "D": "四十"
    },
    "answer": "C",
    "explanation": ""
  },
  {
    "id": 64,
    "number": 64,
    "type": "single",
    "question": "根据《中华人民共和国行政许可法》，临时性的行政许可实施满（ ）需要继续实施的，应当提请本级人民代表大会及其常务委员会制定地方性法规。",
    "options": {
      "A": "半年",
      "B": "一年",
      "C": "两年",
      "D": "三年"
    },
    "answer": "B",
    "explanation": ""
  },
  {
    "id": 65,
    "number": 65,
    "type": "single",
    "question": "根据《中华人民共和国行政许可法》，受委托行政机关在委托范围内，以委托行政机关名义实施行政许可。（ ）对受委托行政机关实施行政许可的行为后果承担法律责任。",
    "options": {
      "A": "委托行政机关",
      "B": "委托行政机关所属人民政府",
      "C": "受委托行政机关",
      "D": "受委托行政机关所属人民政府"
    },
    "answer": "A",
    "explanation": ""
  },
  {
    "id": 66,
    "number": 66,
    "type": "single",
    "question": "根据《中华人民共和国行政许可法》，行政机关受理或者不予受理行政许可申请，应当出具加盖本行政机关（ ）的书面凭证。",
    "options": {
      "A": "专用印章和注明机关名称",
      "B": "专用印章和注明机关简称",
      "C": "专用印章和注明机关联系人",
      "D": "专用印章和注明日期"
    },
    "answer": "D",
    "explanation": ""
  },
  {
    "id": 67,
    "number": 67,
    "type": "single",
    "question": "根据《中华人民共和国行政许可法》，符合法定条件、标准的，申请人有依法取得行政许可的平等权利，行政机关不得（ ）任何人。",
    "options": {
      "A": "拒绝",
      "B": "漠视",
      "C": "歧视",
      "D": "敷衍"
    },
    "answer": "C",
    "explanation": ""
  },
  {
    "id": 68,
    "number": 68,
    "type": "single",
    "question": "根据《中华人民共和国行政许可法》，（ ）应当建立健全对行政机关实施行政许可的监督制度，加强对行政机关实施行政许可的监督检查。",
    "options": {
      "A": "本级人民政府",
      "B": "市级以上人民政府",
      "C": "上级人民政府",
      "D": "县级以上人民政府"
    },
    "answer": "D",
    "explanation": ""
  },
  {
    "id": 69,
    "number": 69,
    "type": "single",
    "question": "根据《中华人民共和国行政许可法》，（ ）应当对公民、法人或者其他组织从事行政许可事项的活动实施有效监督。",
    "options": {
      "A": "行政机关",
      "B": "县级以上人民政府",
      "C": "监察机关",
      "D": "各地区"
    },
    "answer": "A",
    "explanation": ""
  },
  {
    "id": 70,
    "number": 70,
    "type": "single",
    "question": "《中华人民共和国行政许可法》规定，经国务院批准，（ ）人民政府根据精简、统一、效能的原则，可以决定一个行政机关行使有关行政机关的行政许可权。",
    "options": {
      "A": "市级以上",
      "B": "设区的市",
      "C": "县级以上",
      "D": "省、自治区、直辖市"
    },
    "answer": "D",
    "explanation": ""
  },
  {
    "id": 71,
    "number": 71,
    "type": "single",
    "question": "下列属于《中华人民共和国行政许可法》规定的行政许可的是（ ）？",
    "options": {
      "A": "知识产权局授予某发明人专利权",
      "B": "产品质量认证",
      "C": "发给采矿证",
      "D": "授予荣誉称号"
    },
    "answer": "C",
    "explanation": ""
  },
  {
    "id": 72,
    "number": 72,
    "type": "single",
    "question": "根据《中华人民共和国行政许可法》，行政许可申请人以隐瞒有关情况或者提供虚假材料等方式取得属于直接关系公共安全、人身健康、生命财产安全事项的，申请人在（ ）内不得再次申请该行政许可。",
    "options": {
      "A": "半年",
      "B": "一年",
      "C": "三年",
      "D": "五年"
    },
    "answer": "B",
    "explanation": ""
  },
  {
    "id": 73,
    "number": 73,
    "type": "single",
    "question": "根据《中华人民共和国行政许可法》，行政许可的实施机关可以对已设定的行政许可的实施情况及存在的必要性适时进行评价，并将意见报告给该行政许可的（ ）。",
    "options": {
      "A": "监察机关",
      "B": "设定机关",
      "C": "审批机关",
      "D": "许可机关"
    },
    "answer": "B",
    "explanation": ""
  },
  {
    "id": 74,
    "number": 74,
    "type": "single",
    "question": "根据《中华人民共和国行政许可法》，个人和组织发现违法从事行政许可事项的活动，有权向（ ）举报，应当及时核实、处理。",
    "options": {
      "A": "监察机关",
      "B": "行政机关",
      "C": "审批机关",
      "D": "设定机关"
    },
    "answer": "B",
    "explanation": ""
  },
  {
    "id": 75,
    "number": 75,
    "type": "single",
    "question": "根据《中华人民共和国行政许可法》，对直接关系公共安全、人身健康、生命财产安全的重要设备、设施，行政机关应当督促设计、建造、安装和使用单位建立相应的（ ）制度。",
    "options": {
      "A": "巡检",
      "B": "规范",
      "C": "标准",
      "D": "自检"
    },
    "answer": "D",
    "explanation": ""
  },
  {
    "id": 76,
    "number": 76,
    "type": "single",
    "question": "根据《中华人民共和国行政许可法》，被许可人以（ ）等不正当手段取得行政许可的，应当予以撤销。",
    "options": {
      "A": "偷窃、欺骗",
      "B": "欺骗、隐瞒",
      "C": "欺骗、贿赂",
      "D": "贿赂、隐瞒"
    },
    "answer": "C",
    "explanation": ""
  },
  {
    "id": 77,
    "number": 77,
    "type": "single",
    "question": "根据《中华人民共和国行政许可法》规定的行政机关实施行政许可的期限以工作日计算，不含（ ）",
    "options": {
      "A": "节假日",
      "B": "传统节日",
      "C": "法定节假日",
      "D": "周末"
    },
    "answer": "C",
    "explanation": ""
  },
  {
    "id": 78,
    "number": 78,
    "type": "single",
    "question": "下列（ ）不是《中华人民共和国行政许可法》的章节内容？",
    "options": {
      "A": "行政许可的实施程序",
      "B": "行政许可的费用",
      "C": "行政许可的注销",
      "D": "变更与延续"
    },
    "answer": "C",
    "explanation": ""
  },
  {
    "id": 79,
    "number": 79,
    "type": "single",
    "question": "为了规范行政许可的设定和实施，保护公民、法人和其他组织的合法权益，维护公共利益和社会秩序，保障和监督行政机关有效实施行政管理，根据（ ），制定《中华人民共和国行政许可法》。",
    "options": {
      "A": "刑法",
      "B": "法律",
      "C": "民法典",
      "D": "宪法"
    },
    "answer": "D",
    "explanation": ""
  },
  {
    "id": 80,
    "number": 80,
    "type": "single",
    "question": "根据《中华人民共和国行政许可法》，行政机关作出准予行政许可的决定，应当自作出决定之日起十日内向申请人颁发、送达行政许可证件，或者（ ）、加盖检验、检测、检疫印章。",
    "options": {
      "A": "加贴标记",
      "B": "加贴标签",
      "C": "加贴说明",
      "D": "加贴注释"
    },
    "answer": "B",
    "explanation": ""
  },
  {
    "id": 81,
    "number": 81,
    "type": "single",
    "question": "在城市规划和管理的框架内，市政府有意组织一场大型的户外音乐节，该活动预计会占用市区内的公共空间在评估该音乐节活动所涉及的行政许可要求时，下列（ ）说法是符合规定的？",
    "options": {
      "A": "音乐节属娱乐活动，需进行简单的登记即可",
      "B": "详细进行环境影响评估，并获取相关部门的批准",
      "C": "只要口头保证，即可免除所有行政许可手续",
      "D": "可直接办理，无需常规的环境和安全评估"
    },
    "answer": "B",
    "explanation": ""
  },
  {
    "id": 82,
    "number": 82,
    "type": "single",
    "question": "某企业计划在城市郊区建设一座新的化工厂关于此项目的行政许可设定，以下说法正确的是（ ）。",
    "options": {
      "A": "化工厂建设在城市郊区，无需设定行政许可",
      "B": "是市场竞争机制能够有效调节的事项，无需设定",
      "C": "应当设定，以确保环境安全和公众健康",
      "D": "无需设定，公民的生计比环境保护重要得多"
    },
    "answer": "C",
    "explanation": ""
  },
  {
    "id": 83,
    "number": 83,
    "type": "single",
    "question": "根据《中华人民共和国行政许可法》，行政许可的设定机关应当（ ）对其设定的行政许可进行评价。",
    "options": {
      "A": "每年",
      "B": "每两年",
      "C": "每五年",
      "D": "定期"
    },
    "answer": "D",
    "explanation": ""
  },
  {
    "id": 84,
    "number": 84,
    "type": "single",
    "question": "根据《中华人民共和国行政许可法》，行政许可直接涉及申请人与他人之间重大利益关系的，行政机关在作出行政许可决定前，应当告知申请人、利害关系人享有（ ）的权利。",
    "options": {
      "A": "要求听证",
      "B": "要求变更",
      "C": "要求延续",
      "D": "要求暂停"
    },
    "answer": "A",
    "explanation": ""
  },
  {
    "id": 85,
    "number": 85,
    "type": "single",
    "question": "根据《中华人民共和国行政许可法》，关于可以不设行政许可不正确的是（ ）？",
    "options": {
      "A": "公民、法人或者其他组织能自主决定的",
      "B": "市场竞争机制能够调节的",
      "C": "行业组织或者中介机构能够被动管理的",
      "D": "行政机关采用事后监督等其他行政管理方式能够解决的"
    },
    "answer": "C",
    "explanation": ""
  },
  {
    "id": 86,
    "number": 86,
    "type": "single",
    "question": "《中华人民共和国行政许可法》中，行政许可是指行政机关根据公民、法人或者（ ）的申请，经依法审查，准予其从事特定活动的行为。",
    "options": {
      "A": "行业组织",
      "B": "法定组织",
      "C": "其他组织",
      "D": "行政组织"
    },
    "answer": "C",
    "explanation": ""
  },
  {
    "id": 87,
    "number": 87,
    "type": "single",
    "question": "根据《中华人民共和国行政许可法》，申请人、利害关系人在被告知听证权利之日起五日内提出听证申请的，行政机关应当在（ ）内组织听证。",
    "options": {
      "A": "五日",
      "B": "十五日",
      "C": "二十日",
      "D": "二十五日"
    },
    "answer": "C",
    "explanation": ""
  },
  {
    "id": 88,
    "number": 88,
    "type": "single",
    "question": "在《广东省优化营商环境条例》中，对于政务服务“一网通办”的推进，下列描述最为准确的是（ ）。",
    "options": {
      "A": "实现政务服务事项的网上办理",
      "B": "涵盖政务服务事项的网上办理、并联审批、信息共享等多个方面",
      "C": "涉及政务服务窗口的整合",
      "D": "强调电子证照的推广使用"
    },
    "answer": "B",
    "explanation": ""
  },
  {
    "id": 89,
    "number": 89,
    "type": "single",
    "question": "《广东省优化营商环境条例》是在（ ）通过并自（ ）起施行的。",
    "options": {
      "A": "2021年通过，2022年7月1日起施行",
      "B": "2022年通过，2023年1月1日起施行",
      "C": "2022年通过，2022年7月1日起施行",
      "D": "2023年通过，2024年1月1日起施行"
    },
    "answer": "C",
    "explanation": ""
  },
  {
    "id": 90,
    "number": 90,
    "type": "single",
    "question": "在《广东省优化营商环境条例》中，（ ）机构负责建立清单管理制度，对涉企经营许可事项进行分类管理。",
    "options": {
      "A": "省人民政府",
      "B": "县级以上人民政府",
      "C": "省人民政府营商环境主管部门",
      "D": "地级以上市人民政府"
    },
    "answer": "C",
    "explanation": ""
  },
  {
    "id": 91,
    "number": 91,
    "type": "single",
    "question": "《广东省优化营商环境条例》中提到的市场主体登记机关及有关部门在办理市场主体注销登记时，对符合条件的市场主体，可以按照（ ）程序办理注销登记。",
    "options": {
      "A": "普通程序",
      "B": "简易程序",
      "C": "常规程序",
      "D": "特殊程序"
    },
    "answer": "B",
    "explanation": ""
  },
  {
    "id": 92,
    "number": 92,
    "type": "single",
    "question": "在《广东省优化营商环境条例》中，关于市场主体开展研究开发活动的税收优惠政策，以下说法不正确的是（ ）。",
    "options": {
      "A": "享受研究开发费用税前加计扣除",
      "B": "科研仪器设备加速折旧",
      "C": "技术开发和转让税收减免",
      "D": "高新技术的前期投资"
    },
    "answer": "D",
    "explanation": ""
  },
  {
    "id": 93,
    "number": 93,
    "type": "single",
    "question": "在《广东省优化营商环境条例》中，行政执法主体在运用互联网、大数据等技术手段开展非现场执法时，（ ）不是其主要考虑的因素。",
    "options": {
      "A": "非现场执法能否实现有效监管",
      "B": "非现场执法的成本",
      "C": "现场执法的必要性",
      "D": "及时进行现场执法的可能性"
    },
    "answer": "B",
    "explanation": ""
  },
  {
    "id": 94,
    "number": 94,
    "type": "single",
    "question": "根据《广东省优化营商环境条例》，市场主体在获取和使用资金、技术等生产要素时应该遵循（ ）原则。",
    "options": {
      "A": "先到先得原则",
      "B": "平等获取原则",
      "C": "按需分配原则",
      "D": "市场竞争原则"
    },
    "answer": "B",
    "explanation": ""
  },
  {
    "id": 95,
    "number": 95,
    "type": "single",
    "question": "根据《广东省优化营商环境条例》，县级以上人民政府自然资源部门及有关部门应当实行（ ）机制。",
    "options": {
      "A": "产业用地全周期管理",
      "B": "产业用地市场化管理",
      "C": "产业用地年度管理",
      "D": "产业用地弹性管理"
    },
    "answer": "A",
    "explanation": ""
  },
  {
    "id": 96,
    "number": 96,
    "type": "single",
    "question": "根据《广东省优化营商环境条例》，各级人民政府及其有关部门在行政审批过程中需要委托中介服务机构开展技术性服务的，应当通过（ ）方式选择中介服务机构，并自行承担服务费用，不得转嫁给市场主体。",
    "options": {
      "A": "竞争性",
      "B": "自主选取",
      "C": "定期轮换",
      "D": "平均分配"
    },
    "answer": "A",
    "explanation": ""
  },
  {
    "id": 97,
    "number": 97,
    "type": "single",
    "question": "一些地方政府规定本地工程项目必须使用本地企业的产品或者服务，根据《广东省优化营商环境条例》，这种行为属于（ ）。",
    "options": {
      "A": "市场准入限制",
      "B": "歧视性政策",
      "C": "行政干预",
      "D": "招商壁垒"
    },
    "answer": "A",
    "explanation": ""
  },
  {
    "id": 98,
    "number": 98,
    "type": "single",
    "question": "某市的两家大型超市因为市场份额竞争，私下达成了一个价格协议，限制了特定商品的售价。根据《广东省优化营商环境条例》，关于此行为，以下描述正确的是（ ）。",
    "options": {
      "A": "该行为是市场主体的正常经营策略，无需监管干预",
      "B": "市场监管部门应依据反垄断法，调查并可能采取执法措施",
      "C": "该行为有助于维护市场秩序，防止价格战",
      "D": "政府应直接介入，通过行政手段调整商品价格"
    },
    "answer": "B",
    "explanation": ""
  },
  {
    "id": 99,
    "number": 99,
    "type": "single",
    "question": "在某电商平台中，一家具有市场支配地位的商家通过技术手段，对使用不同浏览器的消费者展示不同的价格。根据《广东省优化营商环境条例》，对于此行为，下列选项正确的是（ ）。",
    "options": {
      "A": "该行为属于个性化营销，无需监管",
      "B": "该行为涉嫌滥用市场支配地位，应受到监管",
      "C": "该行为有利于增加平台的多样性，应得到鼓励",
      "D": "该行为属于消费者自主选择的范畴，政府不应干预"
    },
    "answer": "B",
    "explanation": ""
  },
  {
    "id": 100,
    "number": 100,
    "type": "single",
    "question": "一家连锁超市计划在某地扩张分店，当地政府部门要求其每个分店的营业面积必须达到一定的标准。根据《广东省优化营商环境条例》，以下说法正确的是（ ）。",
    "options": {
      "A": "合理且有助于保障消费者的购物体验",
      "B": "违反了市场准入负面清单制度，属于对营业面积的不合理限制",
      "C": "是地方政府对商业规划的合理要求",
      "D": "连锁超市应当遵守，因为这是地方政府的行政权力"
    },
    "answer": "B",
    "explanation": ""
  }
]